sage_dev_toolkit/__init__.pyc
sage_dev_toolkit/__pycache__/__init__.cpython-310.pyc
sage_dev_toolkit/__pycache__/__init__.cpython-311.pyc
sage_dev_toolkit/cli/__init__.pyc
sage_dev_toolkit/cli/main.pyc
sage_dev_toolkit/cli/__pycache__/__init__.cpython-310.pyc
sage_dev_toolkit/cli/__pycache__/__init__.cpython-311.pyc
sage_dev_toolkit/cli/__pycache__/main.cpython-310.pyc
sage_dev_toolkit/cli/__pycache__/main.cpython-311.pyc
sage_dev_toolkit/cli/commands/__init__.pyc
sage_dev_toolkit/cli/commands/analyze.pyc
sage_dev_toolkit/cli/commands/check_dependency.pyc
sage_dev_toolkit/cli/commands/clean.pyc
sage_dev_toolkit/cli/commands/common.pyc
sage_dev_toolkit/cli/commands/home.pyc
sage_dev_toolkit/cli/commands/package.pyc
sage_dev_toolkit/cli/commands/publish.pyc
sage_dev_toolkit/cli/commands/pypi.pyc
sage_dev_toolkit/cli/commands/report.pyc
sage_dev_toolkit/cli/commands/status.pyc
sage_dev_toolkit/cli/commands/test.pyc
sage_dev_toolkit/cli/commands/version.pyc
sage_dev_toolkit/cli/commands/__pycache__/__init__.cpython-310.pyc
sage_dev_toolkit/cli/commands/__pycache__/__init__.cpython-311.pyc
sage_dev_toolkit/cli/commands/__pycache__/analyze.cpython-310.pyc
sage_dev_toolkit/cli/commands/__pycache__/analyze.cpython-311.pyc
sage_dev_toolkit/cli/commands/__pycache__/check_dependency.cpython-310.pyc
sage_dev_toolkit/cli/commands/__pycache__/check_dependency.cpython-311.pyc
sage_dev_toolkit/cli/commands/__pycache__/clean.cpython-310.pyc
sage_dev_toolkit/cli/commands/__pycache__/clean.cpython-311.pyc
sage_dev_toolkit/cli/commands/__pycache__/common.cpython-310.pyc
sage_dev_toolkit/cli/commands/__pycache__/common.cpython-311.pyc
sage_dev_toolkit/cli/commands/__pycache__/compile.cpython-310.pyc
sage_dev_toolkit/cli/commands/__pycache__/home.cpython-310.pyc
sage_dev_toolkit/cli/commands/__pycache__/home.cpython-311.pyc
sage_dev_toolkit/cli/commands/__pycache__/package.cpython-310.pyc
sage_dev_toolkit/cli/commands/__pycache__/package.cpython-311.pyc
intellistream_sage_dev_toolkit-0.1.4.dist-info/METADATA
intellistream_sage_dev_toolkit-0.1.4.dist-info/WHEEL
intellistream_sage_dev_toolkit-0.1.4.dist-info/entry_points.txt
intellistream_sage_dev_toolkit-0.1.4.dist-info/top_level.txt
intellistream_sage_dev_toolkit-0.1.4.dist-info/RECORD
